Metadata-Version: 2.1
Name: odoo-addon-mis_builder_demo
Version: 18.0.1.0.0.2
Requires-Python: >=3.10
Requires-Dist: odoo-addon-mis_builder_budget==18.0.*
Requires-Dist: odoo==18.0.*
Summary: Demo addon for MIS Builder
Home-page: https://github.com/OCA/mis-builder
License: AGPL-3
Author: ACSONE SA/NV, Odoo Community Association (OCA)
Author-email: support@odoo-community.org
Classifier: Programming Language :: Python
Classifier: Framework :: Odoo
Classifier: Framework :: Odoo :: 18.0
Classifier: License :: OSI Approved :: GNU Affero General Public License v3
Classifier: Development Status :: 3 - Alpha
